curious_varvara/__init__.py
curious_varvara/module.py
curious_varvara-0.0.1.dist-info/LICENSE
curious_varvara-0.0.1.dist-info/METADATA
curious_varvara-0.0.1.dist-info/WHEEL
curious_varvara-0.0.1.dist-info/top_level.txt
curious_varvara-0.0.1.dist-info/RECORD
