Metadata-Version: 2.1
Name: curious-varvara
Version: 0.0.1
Summary: Tiny package to check availability of a website
Author-email: Nikolai Vishniakov <nick@nobazar.ru>
Project-URL: homepage, https://github.com/cherryoff/curious-varvara
Requires-Python: >=3.8
License-File: LICENSE
Provides-Extra: dev
Requires-Dist: pytest; extra == "dev"
